LICENSE.md
MANIFEST.in
README.rst
pyproject.toml
requirements.core.txt
setup.py
core_curate_registry_app/__init__.py
core_curate_registry_app/settings.py
core_curate_registry_app/urls.py
core_curate_registry_app.egg-info/PKG-INFO
core_curate_registry_app.egg-info/SOURCES.txt
core_curate_registry_app.egg-info/dependency_links.txt
core_curate_registry_app.egg-info/requires.txt
core_curate_registry_app.egg-info/top_level.txt
core_curate_registry_app/components/__init__.py
core_curate_registry_app/components/curate_data_structure/__init__.py
core_curate_registry_app/components/curate_data_structure/api.py
core_curate_registry_app/rest/__init__.py
core_curate_registry_app/rest/urls.py
core_curate_registry_app/static/core_curate_app/user/js/select_template.raw.js
core_curate_registry_app/static/core_curate_app/user/js/view_data_registry.js
core_curate_registry_app/static/core_curate_app/user/js/view_data_registry.raw.js
core_curate_registry_app/static/core_curate_registry_app/user/css/index.css
core_curate_registry_app/static/core_curate_registry_app/user/js/banner.js
core_curate_registry_app/static/core_curate_registry_app/user/js/enter_data_registry.js
core_curate_registry_app/static/core_curate_registry_app/user/js/enter_data_registry.raw.js
core_curate_registry_app/static/core_curate_registry_app/user/js/role.js
core_curate_registry_app/static/core_curate_registry_app/user/js/start_curate.js
core_curate_registry_app/static/core_curate_registry_app/user/js/title.js
core_curate_registry_app/static/core_curate_registry_app/user/js/title.raw.js
core_curate_registry_app/templates/core_curate_app/user/curate_start.html
core_curate_registry_app/templates/core_curate_app/user/data-entry/enter_data.html
core_curate_registry_app/templates/core_curate_app/user/data-entry/modals/xml-valid-registry.html
core_curate_registry_app/templates/core_curate_app/user/data-review/view_data.html
core_curate_registry_app/templates/core_curate_app/user/data-review/modals/save-form-registry.html
core_curate_registry_app/templates/core_curate_registry_app/user/curate.html
core_curate_registry_app/templates/core_curate_registry_app/user/index.html
core_curate_registry_app/utils/__init__.py
core_curate_registry_app/utils/jquery.py
