Metadata-Version: 2.1
Name: core-curate-registry-app
Version: 2.19.0
Summary: Curation functionalities specific to Registry applications for the curator core project
Home-page: https://github.com/usnistgov/core_curate_registry_app
Author: NIST IT Lab
Author-email: itl_inquiries@nist.gov
License-File: LICENSE.md
